README.md
setup.py
labelaction/__init__.py
labelaction/labelaction.py
labelaction.egg-info/PKG-INFO
labelaction.egg-info/SOURCES.txt
labelaction.egg-info/dependency_links.txt
labelaction.egg-info/entry_points.txt
labelaction.egg-info/requires.txt
labelaction.egg-info/top_level.txt