Metadata-Version: 2.1
Name: labelaction
Version: 1.1.1
Summary: A GUI tool for annotating action in video files. 
Author: xie jiefeng
Author-email: p2417822@mpu.edu.mo
Keywords: Action label,Annotation tools,GUI
Classifier: Development Status :: 1 - Planning
Classifier: Intended Audience :: Developers
Classifier: Programming Language :: Python :: 3
Classifier: Operating System :: Unix
Classifier: Operating System :: MacOS :: MacOS X
Classifier: Operating System :: Microsoft :: Windows
Requires-Dist: PyQt5>=5.15.10
Requires-Dist: opencv-python>=4.10.0
Requires-Dist: pandas>=2.2.0
